librelingo_tools/__init__.py
librelingo_tools/challenge_types.py
librelingo_tools/challenges.py
librelingo_tools/cli.py
librelingo_tools/course.py
librelingo_tools/dictionary.py
librelingo_tools/export.py
librelingo_tools/module.py
librelingo_tools/skills.py
librelingo_tools/utils.py
librelingo_tools/yaml_loader.py
librelingo_tools-0.1.4.dist-info/WHEEL
librelingo_tools-0.1.4.dist-info/METADATA
librelingo_tools-0.1.4.dist-info/RECORD
